pyostie/__init__.py
pyostie/convert.py
pyostie/insights_ext.py
pyostie/parsers.py
pyostie/utils.py
Pyostie-2.6.4.dist-info/LICENSE
Pyostie-2.6.4.dist-info/METADATA
Pyostie-2.6.4.dist-info/WHEEL
Pyostie-2.6.4.dist-info/top_level.txt
Pyostie-2.6.4.dist-info/RECORD
