Metadata-Version: 2.1
Name: Pyostie
Version: 2.6.4
Summary: A python package to OCR data and extract text with insights too.
Home-page: https://github.com/anirudhpnbb/Pyostie
Author: Anirudh Palaparthi
Author-email: anirudhpalaparthi@gmail.com
Classifier: Programming Language :: Python :: 3
Classifier: License :: OSI Approved :: MIT License
Classifier: Operating System :: OS Independent
License-File: LICENSE
Requires-Dist: opencv-python
Requires-Dist: numpy
Requires-Dist: pandas
Requires-Dist: PyPDF2
Requires-Dist: pdfplumber
Requires-Dist: xlrd
Requires-Dist: docx2txt
Requires-Dist: pytesseract
Requires-Dist: Pillow
Requires-Dist: SpeechRecognition
